aadocmodule/__init__.py
aadocmodule/__main__.py
aadocmodule/aadoc.py
aadocmodule/command_line.py
aadocmodule/html_helpers_module/__init__.py
aadocmodule/html_helpers_module/html_helpers.py
aadocmodule/stylesheet_source_module/__init__.py
aadocmodule/stylesheet_source_module/stylesheet_source.py
aadocmodule/tags_module/__init__.py
aadocmodule/tags_module/tags.py
aadoc-1.0.1.dist-info/METADATA
aadoc-1.0.1.dist-info/WHEEL
aadoc-1.0.1.dist-info/entry_points.txt
aadoc-1.0.1.dist-info/top_level.txt
aadoc-1.0.1.dist-info/RECORD
